annime/__init__.py
annime/annoy_int.py
annime/datasketch_ann.py
annime/faiss_int.py
annime/hnswlib_int.py
annime/interface_ann.py
annime/ngt_int.py
annime/nmslib_int.py
annime/scann_int.py
benchmarks/__init__.py
benchmarks/benchmarks.py
benchmarks/datasets.py
benchmarks/datasketch_ann.py
benchmarks/definitions.py
benchmarks/distance.py
benchmarks/results.py
benchmarks/sklrn.py
benchmarks/algorithms/__init__.py
benchmarks/algorithms/datasketch/__init__.py
benchmarks/algorithms/datasketch/module.py
benchmarks/algorithms/faiss/__init__.py
benchmarks/algorithms/faiss/module.py
benchmarks/algorithms/hnswlib/__init__.py
benchmarks/algorithms/hnswlib/module.py
benchmarks/src/__init__.py
benchmarks/src/annoy_int.py
benchmarks/src/datasketch_ann.py
benchmarks/src/faiss_int.py
benchmarks/src/hnswlib_int.py
benchmarks/src/interface_ann.py
benchmarks/src/ngt_int.py
benchmarks/src/nmslib_int.py
benchmarks/src/scann_int.py
annime-0.1.0.1.dist-info/LICENSE
annime-0.1.0.1.dist-info/METADATA
annime-0.1.0.1.dist-info/WHEEL
annime-0.1.0.1.dist-info/top_level.txt
annime-0.1.0.1.dist-info/RECORD
