Metadata-Version: 2.1
Name: annime
Version: 0.1.0.1
Summary: ANN-interface library
Home-page: https://github.com/Azherhs/Annime
Author: Avgustin Zhugalov
Author-email: avgustinalex@yandex.ru
License: MIT
Keywords: ann interface metrics
Classifier: Programming Language :: Python :: 3
Classifier: License :: OSI Approved :: MIT License
Classifier: Operating System :: OS Independent
Requires-Python: >=3.6
License-File: LICENSE
Requires-Dist: numpy
Requires-Dist: scipy
Requires-Dist: scikit-learn
Requires-Dist: pytest
Requires-Dist: matplotlib
Requires-Dist: h5py
Requires-Dist: PyYAML
Requires-Dist: hnswlib
Requires-Dist: datasketch
Requires-Dist: faiss-cpu
Requires-Dist: ngt
Requires-Dist: scann
Requires-Dist: annoy
Requires-Dist: nmslib
